[{"content":"eMMC初始化 eMMC命令格式 eMMC响应格式 eMMC时序参数 eMMC标准术语 block：译为数据块，是flash中基本数据的传输单位。\nCID: Device IDentification register 设备识别寄存器，类似于我们的身份证号码。\nCLK: Clock signal，时钟信号。数据传输以处理都需要时钟信号，类似于心脏跳动，从而使各个器官运行。\nCMD: Command line or e•MMC bus command (if extended CMDXX)，指的是host对device传达的指令。\nCRC: Cyclic Redundancy Check 循环冗余校验，一种校验传输数据是否正确的方式。\nCSD: Device Specific Data register，用于保存EMMC运行期间的状态。\nDAT: Data line 数据传输总线，总共有8根（data0~data7），用于host和device之间双向传输数据。\nData Strobe: Return Clock signal used in HS400 mode，该信号线是双向的，在data line 传输数据期间进行选通。类似于开关的功能。\nDISCARD: 是由host发出的命令，用于识别一些不需要的数据区域，比如现在手机永久了会提示内存不足，询问是否需要删除不需要的应用或者设备，此时我们选择不要的数据或者应用并点击OK后，host 就会识别到这些这些应用存在的数据区域进行内部设置mapping table,断开数据映射关系，等待GC。此外，还存在一种Trim 命令也用作删除数据。\nDDR: Dual data rate. 双倍速率传输，指的是数据会在时钟信号的上升沿和下降沿均进行传输。\nDSR: Driver Stage Register 驱动阶段寄存器，用于改变系统性能。\nD-VDD: cache(缓存) 的电压正极，\nD-VSS: cache(缓存) 的电压接地极，\nD-VDDQ: cache(缓存) 的IO(input/output) 电压正极，\nD-VSSQ: cache(缓存) 的IO(input/output) 电压接地极，\ne•MMC: 嵌入式多媒体卡，其cache可进行修改，同时支持单个引脚。\ne 2 •MMC: 嵌入式多媒体卡，其cache可进行修改，同时支持三个引脚。\nEmpty Task Queue: 无任务队列，指的是device的任务队列中无任务的状态，类似于汽车的怠速状态。\nERASE: 一种擦除操作，只是断开了逻辑映射关系，而没有擦除EMMC物理存储单元中的数据。\nFlash：一种可多次编程的非易失性存储器，非易失性指的是器件本身掉电后数据不会丢失。\nGroup: 综合了擦除和写入保护单元的数据块，数据可以被写入。\nHS200: 高速接口时序模式，其数据在时钟频率为200MHz的情况下，使用单倍数据传输模式，数据传输速率达到200MB/s，I/O供电电压为1V8或者1V2\nHS400: 高速双倍数据接口时序模式，其数据在时钟频率为200MHz的情况下，使用双倍数据传输模式，数据传输速率达到400MB/s，I/O供电电压为1V8或者1V2。时钟频率超过50MHz 可被认为是高速信号。\nSDR和DDR的区别是SDR是Data line 总在时钟信号的上升沿传输数据，而DDR是Data line 在时钟信号的上升沿和下降沿均传输数据。所以SDR称为单倍速率，DDR称为双倍速率。\nISI: 码间干扰。setup/hold余量不足，会使信号在传输过程中，每个UI之间的数据产生干扰，导致数据出错。\nOCR: Operation Conditions Register 操作条件寄存器。\nQSR: Queue Status Register 队列状态寄存器。\nRCA: Relative Device Address register 相对设备地址寄存器。\nSSO: Simultaneous Switching Output (referred as certain type of Noise)同步开关输出，参考同步开关噪声。\nTRIM: 一种可以从写入保护组中删除数据的命令，用于删除数据。trim 命令被执行后，读到该区域的数据为‘0’。\nTuning Process: 调试处理，用于host端对输入信号进行调整，寻找合适的采样点，利于高速信号传输期间，保证采样数据的正确性。在device中有专门用于在HS200模式下，供tunning的调谐数据块。\nUI: 单元间隔，作为单bit数据传输时需要的时间。举例：在时钟频率为200MHz时，单倍数据传输模式下，一个UI=1/f=1/200MHz=5ns。而在双倍数据传输模式下，一个UI=1/f/2=1/200MHz/2=2.5ns。\n","date":"2024-03-22T00:00:00Z","image":"https://rinko1017.life/p/emmc-fpga/cover2_hu345348ecef3ff9f835be17a4dd403481_174572_120x120_fill_q75_box_smart1.jpg","permalink":"https://rinko1017.life/p/emmc-fpga/","title":"基于FPGA的eMMC控制器"},{"content":"This article offers a sample of basic Markdown syntax that can be used in Hugo content files, also it shows whether basic HTML elements are decorated with CSS in a Hugo theme.\nHeadings The following HTML \u0026lt;h1\u0026gt;—\u0026lt;h6\u0026gt; elements represent six levels of section headings. \u0026lt;h1\u0026gt; is the highest section level while \u0026lt;h6\u0026gt; is the lowest.\nH1 H2 H3 H4 H5 H6 Paragraph Xerum, quo qui aut unt expliquam qui dolut labo. Aque venitatiusda cum, voluptionse latur sitiae dolessi aut parist aut dollo enim qui voluptate ma dolestendit peritin re plis aut quas inctum laceat est volestemque commosa as cus endigna tectur, offic to cor sequas etum rerum idem sintibus eiur? Quianimin porecus evelectur, cum que nis nust voloribus ratem aut omnimi, sitatur? Quiatem. Nam, omnis sum am facea corem alique molestrunt et eos evelece arcillit ut aut eos eos nus, sin conecerem erum fuga. Ri oditatquam, ad quibus unda veliamenimin cusam et facea ipsamus es exerum sitate dolores editium rerore eost, temped molorro ratiae volorro te reribus dolorer sperchicium faceata tiustia prat.\nItatur? Quiatae cullecum rem ent aut odis in re eossequodi nonsequ idebis ne sapicia is sinveli squiatum, core et que aut hariosam ex eat.\nBlockquotes The blockquote element represents content that is quoted from another source, optionally with a citation which must be within a footer or cite element, and optionally with in-line changes such as annotations and abbreviations.\nBlockquote without attribution Tiam, ad mint andaepu dandae nostion secatur sequo quae. Note that you can use Markdown syntax within a blockquote.\nBlockquote with attribution Don\u0026rsquo;t communicate by sharing memory, share memory by communicating.\n— Rob Pike1\nTables Tables aren\u0026rsquo;t part of the core Markdown spec, but Hugo supports supports them out-of-the-box.\nName Age Bob 27 Alice 23 Inline Markdown within tables Italics Bold Code italics bold code A B C D E F Lorem ipsum dolor sit amet, consectetur adipiscing elit. Phasellus ultricies, sapien non euismod aliquam, dui ligula tincidunt odio, at accumsan nulla sapien eget ex. Proin eleifend dictum ipsum, non euismod ipsum pulvinar et. Vivamus sollicitudin, quam in pulvinar aliquam, metus elit pretium purus Proin sit amet velit nec enim imperdiet vehicula. Ut bibendum vestibulum quam, eu egestas turpis gravida nec Sed scelerisque nec turpis vel viverra. Vivamus vitae pretium sapien Code Blocks Code block with backticks 1 2 3 4 5 6 7 8 9 10 \u0026lt;!doctype html\u0026gt; \u0026lt;html lang=\u0026#34;en\u0026#34;\u0026gt; \u0026lt;head\u0026gt; \u0026lt;meta charset=\u0026#34;utf-8\u0026#34;\u0026gt; \u0026lt;title\u0026gt;Example HTML5 Document\u0026lt;/title\u0026gt; \u0026lt;/head\u0026gt; \u0026lt;body\u0026gt; \u0026lt;p\u0026gt;Test\u0026lt;/p\u0026gt; \u0026lt;/body\u0026gt; \u0026lt;/html\u0026gt; Code block indented with four spaces \u0026lt;!doctype html\u0026gt; \u0026lt;html lang=\u0026quot;en\u0026quot;\u0026gt; \u0026lt;head\u0026gt; \u0026lt;meta charset=\u0026quot;utf-8\u0026quot;\u0026gt; \u0026lt;title\u0026gt;Example HTML5 Document\u0026lt;/title\u0026gt; \u0026lt;/head\u0026gt; \u0026lt;body\u0026gt; \u0026lt;p\u0026gt;Test\u0026lt;/p\u0026gt; \u0026lt;/body\u0026gt; \u0026lt;/html\u0026gt; Diff code block 1 2 3 4 5 [dependencies.bevy] git = \u0026#34;https://github.com/bevyengine/bevy\u0026#34; rev = \u0026#34;11f52b8c72fc3a568e8bb4a4cd1f3eb025ac2e13\u0026#34; - features = [\u0026#34;dynamic\u0026#34;] + features = [\u0026#34;jpeg\u0026#34;, \u0026#34;dynamic\u0026#34;] One line code block 1 \u0026lt;p\u0026gt;A paragraph\u0026lt;/p\u0026gt; List Types Ordered List First item Second item Third item Unordered List List item Another item And another item Nested list Fruit Apple Orange Banana Dairy Milk Cheese Other Elements — abbr, sub, sup, kbd, mark GIF is a bitmap image format.\nH2O\nXn + Yn = Zn\nPress CTRL + ALT + Delete to end the session.\nMost salamanders are nocturnal, and hunt for insects, worms, and other small creatures.\nThe above quote is excerpted from Rob Pike\u0026rsquo;s talk during Gopherfest, November 18, 2015.\u0026#160;\u0026#x21a9;\u0026#xfe0e;\n","date":"2023-09-07T00:00:00Z","permalink":"https://rinko1017.life/p/markdown-syntax-guide/","title":"Markdown Syntax Guide"},{"content":"Hugo theme Stack supports the creation of interactive image galleries using Markdown. It\u0026rsquo;s powered by PhotoSwipe and its syntax was inspired by Typlog.\nTo use this feature, the image must be in the same directory as the Markdown file, as it uses Hugo\u0026rsquo;s page bundle feature to read the dimensions of the image. External images are not supported.\nSyntax 1 ![Image 1](1.jpg) ![Image 2](2.jpg) Result Photo by mymind and Luke Chesser on Unsplash\n","date":"2023-08-26T00:00:00Z","image":"https://rinko1017.life/p/image-gallery/2_hubce42636ecacc1a380b462f3110efcec_37455_120x120_fill_q75_box_smart1.jpg","permalink":"https://rinko1017.life/p/image-gallery/","title":"Image gallery"},{"content":"Stack has built-in support for math typesetting using KaTeX.\nIt\u0026rsquo;s not enabled by default side-wide, but you can enable it for individual posts by adding math: true to the front matter. Or you can enable it side-wide by adding math = true to the params.article section in config.toml.\nInline math This is an inline mathematical expression: $\\varphi = \\dfrac{1+\\sqrt5}{2}= 1.6180339887…$\n1 $\\varphi = \\dfrac{1+\\sqrt5}{2}= 1.6180339887…$ Block math $$ \\varphi = 1+\\frac{1} {1+\\frac{1} {1+\\frac{1} {1+\\cdots} } } $$\n1 2 3 $$ \\varphi = 1+\\frac{1} {1+\\frac{1} {1+\\frac{1} {1+\\cdots} } } $$ $$ f(x) = \\int_{-\\infty}^\\infty\\hat f(\\xi),e^{2 \\pi i \\xi x},d\\xi $$\n1 2 3 $$ f(x) = \\int_{-\\infty}^\\infty\\hat f(\\xi)\\,e^{2 \\pi i \\xi x}\\,d\\xi $$ ","date":"2023-08-24T00:00:00Z","permalink":"https://rinko1017.life/p/math-typesetting/","title":"Math Typesetting"}]